onl/__init__.py
onl/types.py
onl/device/__init__.py
onl/device/base.py
onl/device/udp.py
onl/netdev/__init__.py
onl/netdev/demux.py
onl/netdev/hub.py
onl/netdev/port.py
onl/netdev/port_monitor.py
onl/netdev/red_port.py
onl/netdev/splitter.py
onl/netdev/switch.py
onl/netdev/token_bucket.py
onl/netdev/two_level_token_bucket.py
onl/netdev/wire.py
onl/packet/__init__.py
onl/packet/dist_generator.py
onl/packet/packet.py
onl/packet/proxy_generator.py
onl/packet/proxy_sink.py
onl/packet/sink.py
onl/packet/tcp_generator.py
onl/packet/tcp_sink.py
onl/scheduler/__init__.py
onl/scheduler/base.py
onl/scheduler/drr.py
onl/scheduler/monitor.py
onl/scheduler/rr.py
onl/scheduler/sp.py
onl/scheduler/virtual_clock.py
onl/scheduler/wfq.py
onl/scheduler/wrr.py
onl/sim/__init__.py
onl/sim/core.py
onl/sim/events.py
onl/sim/exceptions.py
onl/sim/rt.py
onl/sim/resources/__init__.py
onl/sim/resources/base.py
onl/sim/resources/container.py
onl/sim/resources/resource.py
onl/sim/resources/store.py
onl/utils/__init__.py
onl/utils/testing.py
onl/utils/timer.py
onl_edu-0.5.dist-info/LICENSE
onl_edu-0.5.dist-info/METADATA
onl_edu-0.5.dist-info/WHEEL
onl_edu-0.5.dist-info/top_level.txt
onl_edu-0.5.dist-info/RECORD
