Metadata-Version: 2.1
Name: onl-edu
Version: 0.5
Summary: onl for education 2023 By USTC
Home-page: https://github.com/onl/OpenNetLab-Edu
Author: zdszero
Author-email: dingzifeng8@gmail.com
License: UNKNOWN
Project-URL: Bug Tracker, https://github.com/onl/OpenNetLab-Edu/issues
Platform: UNKNOWN
Classifier: Programming Language :: Python :: 3
Classifier: License :: OSI Approved :: MIT License
Classifier: Operating System :: OS Independent
Requires-Python: >=3.6
